pointevector/xml_parser/__init__.py
pointevector/xml_parser/validate_config.py
pointevector/xml_parser/xml_parser.py
pointevector_xmlparser-0.0.2.dist-info/LICENSE
pointevector_xmlparser-0.0.2.dist-info/METADATA
pointevector_xmlparser-0.0.2.dist-info/WHEEL
pointevector_xmlparser-0.0.2.dist-info/top_level.txt
pointevector_xmlparser-0.0.2.dist-info/RECORD
